{
  "signal_du_jour": {
    "titre": "Haussier — Impulsion post-FOMC",
    "description": "NQ Futures +2.15% après la décision de la Fed (taux inchangés, signal dovish). VIX en baisse de 4%, EURUSD et or en hausse. Brent chute de 8.5% sur excès d'offre.",
    "biais": "haussier",
    "conviction": "forte",
    "contexte_macro": "La Fed maintient ses taux mais adopte un ton accommodant, soutenant les marchés actions. La chute du Brent et la hausse de l'or reflètent des tensions géopolitiques persistantes et des craintes de ralentissement économique."
  },
  "plan_actions": [
    {
      "heure": "20h40",
      "titre": "CALL NQ Futures ×20 (FOMC)",
      "sens": "CALL",
      "mise": "2000 €",
      "levier": 20,
      "strike_ko": "Strike 24000 / KO 23500",
      "gain_cible": "+25% si NQ +1.5%",
      "plateforme": "sgbourse.fr → Nasdaq 100 → CALL BEST",
      "note": "Entrée immédiate après la décision Fed. Surveillance du VIX et de l'EURUSD pour confirmation.",
      "urgence": "haute"
    },
    {
      "heure": "21h00",
      "titre": "PUT BRENT ×15 (couverture)",
      "sens": "PUT",
      "mise": "1500 €",
      "levier": 15,
      "strike_ko": "Strike 98 / KO 102",
      "gain_cible": "+20% si Brent -2%",
      "plateforme": "bnpparibas.com → Energie → PUT Warrant",
      "note": "Protection contre une éventuelle reprise du Brent après la chute. Stop mental à -40%.",
      "urgence": "normale"
    }
  ],
  "niveaux_cles": [
    {
      "label": "Résistance haute NQ",
      "prix": 24600,
      "type": "resistance",
      "action": "Prendre profits TP1 si atteinte",
      "couleur": "bull"
    },
    {
      "label": "Support NQ",
      "prix": 24200,
      "type": "support",
      "action": "Achat supplémentaire si cassure",
      "couleur": "bear"
    },
    {
      "label": "Seuil Brent",
      "prix": 97,
      "type": "support",
      "action": "Sortie PUT si cassure",
      "couleur": "bear"
    }
  ],
  "alertes": [
    "Surveillance VIX (niveau 24) pour confirmation de la tendance haussière.",
    "FOMC terminé — pas d'autres annonces majeures prévues ce soir."
  ],
  "regles_session": [
    "Stop mental −40% sur chaque position = sortie immédiate",
    "Clôture obligatoire à 22h pour les turbos NQ/indices"
  ],
  "market_strip": {
    "nq": {
      "valeur": "24 470",
      "chg": "+2.15%",
      "dir": "up"
    },
    "cac40": {
      "valeur": "7 726",
      "chg": "+0.86%",
      "dir": "up"
    },
    "brent": {
      "valeur": "$98.8",
      "chg": "-8.50%",
      "dir": "dn"
    },
    "vix": {
      "valeur": "25.7",
      "chg": "-4.00%",
      "dir": "dn"
    },
    "eurusd": {
      "valeur": "1.1623",
      "chg": "+0.41%",
      "dir": "up"
    },
    "gold": {
      "valeur": "4407.90",
      "chg": "+1.21%",
      "dir": "up"
    },
    "us10y": {
      "valeur": "4.334",
      "chg": "-1.30%",
      "dir": "dn"
    }
  },
  "pea_note": "PEA — Ne pas toucher. Capital day trading dédié uniquement.",
  "edition": "20h37 CET",
  "mode": "fomc",
  "timestamp": "2026-03-23T20:37:49.405117+01:00",
  "date_fr": "Monday 23 march 2026"
}