{
  "signal_du_jour": {
    "titre": "Biais neutre — JPMorgan alerte sur les prochaines baisses de taux Fed",
    "description": "NQ Futures +0.52%, VIX en hausse à 24.48 (+2.43%). JPMorgan met en garde contre un possible durcissement des conditions monétaires malgré les anticipations de baisses de taux.",
    "biais": "neutre",
    "conviction": "modérée",
    "contexte_macro": "Marchés en attente des prochaines données économiques US. Sentiment global stable malgré les alertes de JPMorgan sur la politique monétaire."
  },
  "plan_actions": [
    {
      "heure": "22h00",
      "titre": "PUT NQ Futures ×18 (Turbo BEST SG)",
      "sens": "PUT",
      "mise": "1200 €",
      "levier": 18,
      "strike_ko": "Strike 24000 / KO 24600",
      "gain_cible": "+28% si NQ -1.2%",
      "plateforme": "sgbourse.fr → Nasdaq 100 → PUT BEST",
      "note": "Entrée 22h00–22h15. Stop mental -40%. Surveillance VIX >25 → levier max ×18.",
      "urgence": "normale"
    }
  ],
  "niveaux_cles": [
    {
      "label": "Support NQ",
      "prix": 24200,
      "type": "support",
      "action": "Entrée PUT si cassé",
      "couleur": "bear"
    },
    {
      "label": "Résistance NQ",
      "prix": 24500,
      "type": "resistance",
      "action": "TP1 si atteint",
      "couleur": "bull"
    }
  ],
  "alertes": [
    "JPMorgan alerte sur Fed — surveillance 22h30 CET",
    "Données US ISM Services à 22h00 CET"
  ],
  "regles_session": [
    "Stop mental −40% = sortie immédiate",
    "Actions FR → clôture obligatoire 17h30",
    "Turbos NQ → cotent jusqu'à 22h CET"
  ],
  "market_strip": {
    "nq": {
      "valeur": "24 339",
      "chg": "+0.52%",
      "dir": "up"
    },
    "cac40": {
      "valeur": "7 962",
      "chg": "-0.16%",
      "dir": "dn"
    },
    "brent": {
      "valeur": "$109.8",
      "chg": "-0.01%",
      "dir": "dn"
    },
    "vix": {
      "valeur": "24.5",
      "chg": "+2.43%",
      "dir": "up"
    },
    "gold": {
      "valeur": "$4 678.70",
      "chg": "+0.27%",
      "dir": "up"
    },
    "eurusd": {
      "valeur": "1.1546",
      "chg": "+0.21%",
      "dir": "up"
    },
    "us10y": {
      "valeur": "4.335%",
      "chg": "+0.51%",
      "dir": "up"
    }
  },
  "pea_note": "PEA — Ne pas toucher. Focus sur NQ Futures.",
  "edition": "21:43 CET",
  "mode": "normal",
  "timestamp": "2026-04-06T21:43:12.005191+02:00",
  "date_fr": "Lundi 6 avril 2026"
}